LICENSE
seleniumtabs/__init__.py
seleniumtabs/browser.py
seleniumtabs/browser_management.py
seleniumtabs/css_selectors.py
seleniumtabs/exceptions.py
seleniumtabs/js_scripts/jquery_scripts.py
seleniumtabs/js_scripts/scripts.py
seleniumtabs/log_config/log_config.yaml
seleniumtabs/read_envs.py
seleniumtabs/schedule_tasks.py
seleniumtabs/session.py
seleniumtabs/settings.py
seleniumtabs/tabs.py
seleniumtabs/tests/conftest.py
seleniumtabs/tests/test_basic_function.py
seleniumtabs/tests/test_task_scheduler.py
seleniumtabs/utils/__init__.py
seleniumtabs/utils/core.py
seleniumtabs/utils/urls.py
seleniumtabs/wait.py
seleniumtabs-2.1.1.dist-info/LICENSE
seleniumtabs-2.1.1.dist-info/METADATA
seleniumtabs-2.1.1.dist-info/WHEEL
seleniumtabs-2.1.1.dist-info/RECORD
