Metadata-Version: 2.1
Name: seleniumtabs
Version: 2.1.1
Summary: Selenium with tab management in Python
Home-page: https://github.com/TheConfused/selenium-tabs
License: MIT
Keywords: selenium tabs,selenium python,selenium python automation,python automation
Author: Vishal Kumar Mishra
Author-email: vishal.k.mishra2@gmail.com
Requires-Python: >=3.13,<4.0
Classifier: License :: OSI Approved :: MIT License
Classifier: Programming Language :: Python :: 3
Classifier: Programming Language :: Python :: 3.13
Requires-Dist: PyYAML (>=6.0.1)
Requires-Dist: browserjquery (>=2.0.1,<3.0.0)
Requires-Dist: django-environ (>=0.11.2)
Requires-Dist: fake-useragent (>=2.2.0,<3.0.0)
Requires-Dist: pyquery (>=2.0.0)
Requires-Dist: pytest-cov (>=6.2.1,<7.0.0)
Requires-Dist: python-dotenv (>=1.0.0)
Requires-Dist: schedule (>=1.2.2)
Requires-Dist: selenium (>=4.12.0)
Requires-Dist: tldextract (>=5.1.2,<6.0.0)
Requires-Dist: webdriver-manager (>=4.0.2)
Project-URL: Repository, https://github.com/TheConfused/selenium-tabs
